<?xml version="1.0" encoding="utf-8"?>
<LanguageData>

  <FT_PowerPole.label>power pole</FT_PowerPole.label>
  <FT_PowerPole.description>A concrete power pole, using tin or copper cables to carry an electrical current.
Connect to other power poles using the 'link' button, or select multiple power poles and press the 'auto-link' button.</FT_PowerPole.description>
  <FT_PowerPole_Blueprint.label>power pole (blueprint)</FT_PowerPole_Blueprint.label>
  <FT_PowerPole_Blueprint_Install.label>power pole (blueprint)</FT_PowerPole_Blueprint_Install.label>
  <FT_PowerPole_Frame.label>power pole (building)</FT_PowerPole_Frame.label>
  <FT_PowerPole_Frame.description>A concrete power pole, using tin or copper cables to carry an electrical current.
Connect to other power poles using the 'link' button, or select multiple power poles and press the 'auto-link' button.</FT_PowerPole_Frame.description>


  <!-- 含路燈 -->

  <FT_PowerPole_Lamp.label>power pole (street lamp)</FT_PowerPole_Lamp.label>
  <FT_PowerPole_Lamp.description>A concrete power pole, using tin or copper cables to carry an electrical current.
Connect to other power poles using the 'link' button, or select multiple power poles and press the 'auto-link' button.</FT_PowerPole_Lamp.description>
  <FT_PowerPole_Lamp_Blueprint.label>power pole (street lamp) (blueprint)</FT_PowerPole_Lamp_Blueprint.label>
  <FT_PowerPole_Lamp_Blueprint_Install.label>power pole (street lamp) (blueprint)</FT_PowerPole_Lamp_Blueprint_Install.label>
  <FT_PowerPole_Lamp_Frame.label>power pole (street lamp) (building)</FT_PowerPole_Lamp_Frame.label>
  <FT_PowerPole_Lamp_Frame.description>A concrete power pole, using tin or copper cables to carry an electrical current.
Connect to other power poles using the 'link' button, or select multiple power poles and press the 'auto-link' button.</FT_PowerPole_Lamp_Frame.description>

  <FT_DistributionBox.label>distribution box</FT_DistributionBox.label>
  <FT_DistributionBox.description>A metal box on a concrete foundation connects to power networks via conduit to extend the range at which electronics can connect to said conduits. Proper implementation can triple the range at which electric current can be utilized.</FT_DistributionBox.description>


</LanguageData>