<?xml version="1.0" encoding="utf-8"?>
<LanguageData>

	<Light_Leather.label>Легкая кожа</Light_Leather.label>
	<Light_Leather.description>Легкая шкура животных, подходящая для создания одежды или мебели.</Light_Leather.description>
	<Light_Leather.stuffProps.stuffAdjective>легкой кожи</Light_Leather.stuffProps.stuffAdjective>
	
	<Regular_Leather.label>Кожа</Regular_Leather.label>
	<Regular_Leather.description>Шкура животных, подходящая для создания одежды или мебели.</Regular_Leather.description>
	<Regular_Leather.stuffProps.stuffAdjective>кожи</Regular_Leather.stuffProps.stuffAdjective>
	
	<Thick_Leather.label>Толстая кожа</Thick_Leather.label>
	<Thick_Leather.description>Прочная шкура животных, отлично подходящая для создания доспехов и одежды.</Thick_Leather.description>
	<Thick_Leather.stuffProps.stuffAdjective>толстой кожи</Thick_Leather.stuffProps.stuffAdjective>
	
	<Regular_Fur.label>Мех</Regular_Fur.label>
	<Regular_Fur.description>Мех животного, защищающий в холодную погоду. Хорошо подходит в пошиве одежды.</Regular_Fur.description>
	<Regular_Fur.stuffProps.stuffAdjective>меха</Regular_Fur.stuffProps.stuffAdjective>
	
	<Regular_Wool.label>Шерсть</Regular_Wool.label>
	<Regular_Wool.description>Теплая и мягкая шерсть животного. Отлично подходит для пошива теплой одежды.</Regular_Wool.description>
	<Regular_Wool.stuffProps.stuffAdjective>шерсти</Regular_Wool.stuffProps.stuffAdjective>
	
	<Warm_Fur.label>Теплый мех</Warm_Fur.label>
	<Warm_Fur.description>Мягкий и теплый мех животного. Выглядит стильно и отлично согревает зимой.</Warm_Fur.description>
	<Warm_Fur.stuffProps.stuffAdjective>теплого меха</Warm_Fur.stuffProps.stuffAdjective>
	
	<ThrumboFur.label>Мех трумбо</ThrumboFur.label>
	<ThrumboFur.description>Крайне прочный и теплый мех огромного трумбо. Внешняя жесткость и твердость позволяют меху использоваться в качестве защитного покрытия.</ThrumboFur.description>
	<ThrumboFur.stuffProps.stuffAdjective>меха трумбо</ThrumboFur.stuffProps.stuffAdjective>
	
</LanguageData>