<?xml version="1.0" encoding="utf-8"?>
<Defs>
	<ThingDef ParentName="BaseFilth">
		<defName>Filth_Torf</defName>
		<label>Peat heap</label>
		<description>Will light up if set on fire.</description>
		<useHitPoints>true</useHitPoints>
		<statBases>
			<Beauty>-10</Beauty>
			<Cleanliness>-15</Cleanliness>
			<MaxHitPoints>1000</MaxHitPoints>
			<Flammability>2.0</Flammability>
		</statBases>
		<graphicData>
			<texPath>Things/Filth/LiquidFuel</texPath>
			<color>(91,75,65,97)</color>
		</graphicData>
		<filth>
			<ignoreFilthMultiplierStat>true</ignoreFilthMultiplierStat>
			<disappearsInDays>5~10</disappearsInDays>
			<rainWashes>false</rainWashes>
			<cleaningWorkToReduceThickness>70</cleaningWorkToReduceThickness>
			<canFilthAttach>true</canFilthAttach>
			<maxThickness>1</maxThickness>
			<cleaningSound>Interact_CleanFilth_Fluid</cleaningSound>
			<placementMask>None</placementMask>
		</filth>
	</ThingDef>
	<ThingDef ParentName="BaseFilth">
		<defName>Filth_FireFog</defName>
		<label>fire fog</label>
		<useHitPoints>true</useHitPoints>
		<statBases>
			<Beauty>-25</Beauty>
			<Cleanliness>-5</Cleanliness>
			<Flammability>4</Flammability>
			<MaxHitPoints>200</MaxHitPoints>
		</statBases>
		<graphicData>
			<texPath>Things/Filth/FireFoam</texPath>
			<color>(180, 180, 180, 100)</color>
			<drawSize>2</drawSize>
		</graphicData>
		<filth>
			<ignoreFilthMultiplierStat>true</ignoreFilthMultiplierStat>
			<disappearsInDays>2~4</disappearsInDays>
			<rainWashes>false</rainWashes>
			<cleaningWorkToReduceThickness>100</cleaningWorkToReduceThickness>
			<canFilthAttach>true</canFilthAttach>
			<allowsFire>true</allowsFire>
			<cleaningSound>Interact_CleanFilth_Fluid</cleaningSound>
		</filth>
	</ThingDef>
	<ThingDef ParentName="BaseFilth">
		<defName>Filth_AcidBombing</defName>
		<label>bombardier acid</label>
		<thingClass>ProjectParagon.Core.Things.Filth_AcidBombing</thingClass>
		<useHitPoints>true</useHitPoints>
		<statBases>
			<Beauty>-50</Beauty>
			<Cleanliness>-25</Cleanliness>
			<Flammability>0</Flammability>
		</statBases>
		<graphicData>
			<texPath>Things/Filth/FireFoam</texPath>
			<color>(179, 185, 73, 180)</color>
			<drawSize>2</drawSize>
		</graphicData>
		<filth>
			<ignoreFilthMultiplierStat>true</ignoreFilthMultiplierStat>
			<disappearsInDays>0.25~0.3</disappearsInDays>
			<rainWashes>false</rainWashes>
			<cleaningWorkToReduceThickness>500</cleaningWorkToReduceThickness>
			<canFilthAttach>true</canFilthAttach>
			<allowsFire>true</allowsFire>
			<cleaningSound>Interact_CleanFilth_Fluid</cleaningSound>
		</filth>
		<tickerType>Normal</tickerType>
	</ThingDef>
	<ThingDef ParentName="BaseFilth">
		<defName>Filth_OrganicProcessing</defName>
		<label>recycler acid</label>
		<thingClass>ProjectParagon.Core.Things.Filth_OrganicProcessing</thingClass>
		<useHitPoints>true</useHitPoints>
		<statBases>
			<Beauty>-50</Beauty>
			<Cleanliness>-25</Cleanliness>
			<Flammability>0</Flammability>
		</statBases>
		<graphicData>
			<texPath>Things/Filth/FireFoam</texPath>
			<color>(179, 185, 73, 180)</color>
			<drawSize>2</drawSize>
		</graphicData>
		<filth>
			<ignoreFilthMultiplierStat>true</ignoreFilthMultiplierStat>
			<disappearsInDays>0.05~0.1</disappearsInDays>
			<rainWashes>false</rainWashes>
			<cleaningWorkToReduceThickness>500</cleaningWorkToReduceThickness>
			<canFilthAttach>true</canFilthAttach>
			<allowsFire>true</allowsFire>
			<cleaningSound>Interact_CleanFilth_Fluid</cleaningSound>
		</filth>
		<tickerType>Normal</tickerType>
	</ThingDef>
	<ThingDef ParentName="BaseFilth">
		<defName>Filth_Oil</defName>
		<label>oil puddle</label>
		<description>A puddle of flammable oil.</description>
		<useHitPoints>true</useHitPoints>
		<statBases>
			<Beauty>-25</Beauty>
			<Cleanliness>-50</Cleanliness>
			<MaxHitPoints>800</MaxHitPoints>
			<Flammability>0.7</Flammability>
		</statBases>
		<graphicData>
			<texPath>Things/Filth/LiquidFuel</texPath>
			<color>(38, 38, 38)</color>
		</graphicData>
		<filth>
			<ignoreFilthMultiplierStat>true</ignoreFilthMultiplierStat>
			<disappearsInDays>400~600</disappearsInDays>
			<rainWashes>false</rainWashes>
			<cleaningWorkToReduceThickness>30000</cleaningWorkToReduceThickness>
			<canFilthAttach>true</canFilthAttach>
			<maxThickness>50</maxThickness>
			<cleaningSound>Interact_CleanFilth_Fluid</cleaningSound>
		</filth>
	</ThingDef>
	<ThingDef ParentName="BaseFilth">
		<defName>Filth_LightOil</defName>
		<label>light oil puddle</label>
		<description>A puddle of flammable light oil.</description>
		<useHitPoints>true</useHitPoints>
		<statBases>
			<Beauty>-15</Beauty>
			<Cleanliness>-15</Cleanliness>
			<MaxHitPoints>500</MaxHitPoints>
			<Flammability>8.0</Flammability>
		</statBases>
		<graphicData>
			<texPath>Things/Filth/LiquidFuel</texPath>
			<color>(191, 212, 119)</color>
		</graphicData>
		<filth>
			<ignoreFilthMultiplierStat>true</ignoreFilthMultiplierStat>
			<disappearsInDays>4~9</disappearsInDays>
			<rainWashes>true</rainWashes>
			<cleaningWorkToReduceThickness>4000</cleaningWorkToReduceThickness>
			<canFilthAttach>true</canFilthAttach>
			<maxThickness>50</maxThickness>
			<cleaningSound>Interact_CleanFilth_Fluid</cleaningSound>
		</filth>
	</ThingDef>
	<ThingDef ParentName="BaseFilth">
		<defName>Filth_MediumOil</defName>
		<label>medium oil puddle</label>
		<description>A puddle of flammable medium oil.</description>
		<useHitPoints>true</useHitPoints>
		<statBases>
			<Beauty>-15</Beauty>
			<Cleanliness>-15</Cleanliness>
			<MaxHitPoints>500</MaxHitPoints>
			<Flammability>5.0</Flammability>
		</statBases>
		<graphicData>
			<texPath>Things/Filth/LiquidFuel</texPath>
			<color>(77, 59, 89)</color>
		</graphicData>
		<filth>
			<ignoreFilthMultiplierStat>true</ignoreFilthMultiplierStat>
			<disappearsInDays>7~13</disappearsInDays>
			<rainWashes>false</rainWashes>
			<cleaningWorkToReduceThickness>7000</cleaningWorkToReduceThickness>
			<canFilthAttach>true</canFilthAttach>
			<maxThickness>50</maxThickness>
			<cleaningSound>Interact_CleanFilth_Fluid</cleaningSound>
		</filth>
	</ThingDef>
	<ThingDef ParentName="BaseFilth">
		<defName>Filth_HeavyOil</defName>
		<label>heavy oil puddle</label>
		<description>A puddle of flammable heavy oil.</description>
		<useHitPoints>true</useHitPoints>
		<statBases>
			<Beauty>-25</Beauty>
			<Cleanliness>-50</Cleanliness>
			<MaxHitPoints>700</MaxHitPoints>
			<Flammability>0.3</Flammability>
		</statBases>
		<graphicData>
			<texPath>Things/Filth/LiquidFuel</texPath>
			<color>(135, 94, 23)</color>
		</graphicData>
		<filth>
			<ignoreFilthMultiplierStat>true</ignoreFilthMultiplierStat>
			<disappearsInDays>20~40</disappearsInDays>
			<rainWashes>false</rainWashes>
			<cleaningWorkToReduceThickness>30000</cleaningWorkToReduceThickness>
			<canFilthAttach>true</canFilthAttach>
			<maxThickness>50</maxThickness>
			<cleaningSound>Interact_CleanFilth_Fluid</cleaningSound>
		</filth>
	</ThingDef>
	<ThingDef ParentName="BaseFilth">
		<defName>Filth_Diesel</defName>
		<label>Diesel puddle</label>
		<description>A puddle of flammable Diesell.</description>
		<useHitPoints>true</useHitPoints>
		<statBases>
			<Beauty>-25</Beauty>
			<Cleanliness>-50</Cleanliness>
			<MaxHitPoints>700</MaxHitPoints>
			<Flammability>6.0</Flammability>
		</statBases>
		<graphicData>
			<texPath>Things/Filth/LiquidFuel</texPath>
			<color>(154, 163, 119)</color>
		</graphicData>
		<filth>
			<ignoreFilthMultiplierStat>true</ignoreFilthMultiplierStat>
			<disappearsInDays>7~13</disappearsInDays>
			<rainWashes>false</rainWashes>
			<cleaningWorkToReduceThickness>7000</cleaningWorkToReduceThickness>
			<canFilthAttach>true</canFilthAttach>
			<maxThickness>50</maxThickness>
			<cleaningSound>Interact_CleanFilth_Fluid</cleaningSound>
		</filth>
	</ThingDef>
	<ThingDef ParentName="BaseFilth">
		<defName>Filth_Naphtha</defName>
		<label>naphtha puddle</label>
		<description>A puddle of flammable naphtha.</description>
		<useHitPoints>true</useHitPoints>
		<statBases>
			<Beauty>-25</Beauty>
			<Cleanliness>-15</Cleanliness>
			<MaxHitPoints>400</MaxHitPoints>
			<Flammability>4.5</Flammability>
		</statBases>
		<graphicData>
			<texPath>Things/Filth/LiquidFuel</texPath>
			<color>(156, 179, 45)</color>
		</graphicData>
		<filth>
			<ignoreFilthMultiplierStat>true</ignoreFilthMultiplierStat>
			<disappearsInDays>7~13</disappearsInDays>
			<rainWashes>false</rainWashes>
			<cleaningWorkToReduceThickness>7000</cleaningWorkToReduceThickness>
			<canFilthAttach>true</canFilthAttach>
			<maxThickness>50</maxThickness>
			<cleaningSound>Interact_CleanFilth_Fluid</cleaningSound>
		</filth>
	</ThingDef>
	<ThingDef ParentName="BaseFilth">
		<defName>Filth_Ethanol</defName>
		<label>Ethanol puddle</label>
		<description>A puddle of flammable Ethanol.</description>
		<useHitPoints>true</useHitPoints>
		<statBases>
			<Beauty>-5</Beauty>
			<Cleanliness>-10</Cleanliness>
			<MaxHitPoints>700</MaxHitPoints>
			<Flammability>0.2</Flammability>
		</statBases>
		<graphicData>
			<texPath>Things/Filth/LiquidFuel</texPath>
			<color>(173, 173, 173)</color>
		</graphicData>
		<filth>
			<ignoreFilthMultiplierStat>true</ignoreFilthMultiplierStat>
			<disappearsInDays>1~3</disappearsInDays>
			<rainWashes>true</rainWashes>
			<cleaningWorkToReduceThickness>2000</cleaningWorkToReduceThickness>
			<canFilthAttach>true</canFilthAttach>
			<maxThickness>50</maxThickness>
			<cleaningSound>Interact_CleanFilth_Fluid</cleaningSound>
		</filth>
	</ThingDef>
	<ThingDef ParentName="BaseFilth">
		<defName>Filth_LiquidFertilizer</defName>
		<label>Liquid fertilizer puddle</label>
		<description>A puddle of flammable fertilizer.</description>
		<useHitPoints>true</useHitPoints>
		<statBases>
			<Beauty>-5</Beauty>
			<Cleanliness>-10</Cleanliness>
			<MaxHitPoints>700</MaxHitPoints>
			<Flammability>1</Flammability>
		</statBases>
		<graphicData>
			<texPath>Things/Filth/LiquidFuel</texPath>
			<color>(133, 95, 110)</color>
		</graphicData>
		<filth>
			<ignoreFilthMultiplierStat>true</ignoreFilthMultiplierStat>
			<disappearsInDays>1~3</disappearsInDays>
			<rainWashes>true</rainWashes>
			<cleaningWorkToReduceThickness>2000</cleaningWorkToReduceThickness>
			<canFilthAttach>true</canFilthAttach>
			<maxThickness>50</maxThickness>
			<cleaningSound>Interact_CleanFilth_Fluid</cleaningSound>
		</filth>
	</ThingDef>
	<ThingDef ParentName="BaseFilth">
		<defName>Filth_Refrigerant</defName>
		<label>Refrigerant puddle</label>
		<description>A puddle of refrigerant.</description>
		<useHitPoints>true</useHitPoints>
		<statBases>
			<Beauty>-5</Beauty>
			<Cleanliness>-10</Cleanliness>
			<MaxHitPoints>700</MaxHitPoints>
			<Flammability>0</Flammability>
		</statBases>
		<graphicData>
			<texPath>Things/Filth/LiquidFuel</texPath>
			<color>(127, 241, 238)</color>
		</graphicData>
		<filth>
			<ignoreFilthMultiplierStat>true</ignoreFilthMultiplierStat>
			<disappearsInDays>0.5~0.75</disappearsInDays>
			<rainWashes>true</rainWashes>
			<cleaningWorkToReduceThickness>250</cleaningWorkToReduceThickness>
			<canFilthAttach>true</canFilthAttach>
			<maxThickness>50</maxThickness>
			<cleaningSound>Interact_CleanFilth_Fluid</cleaningSound>
		</filth>
	</ThingDef>
	<ThingDef ParentName="BaseFilth">
		<defName>Filth_RocketFuel</defName>
		<label>Rocket fuel puddle</label>
		<description>A puddle of flammable rocket fuel.</description>
		<useHitPoints>true</useHitPoints>
		<statBases>
			<Beauty>-25</Beauty>
			<Cleanliness>-50</Cleanliness>
			<MaxHitPoints>700</MaxHitPoints>
			<Flammability>8.0</Flammability>
		</statBases>
		<graphicData>
			<texPath>Things/Filth/LiquidFuel</texPath>
			<color>(170,170,170)</color>
		</graphicData>
		<filth>
			<ignoreFilthMultiplierStat>true</ignoreFilthMultiplierStat>
			<disappearsInDays>7~13</disappearsInDays>
			<rainWashes>false</rainWashes>
			<cleaningWorkToReduceThickness>8000</cleaningWorkToReduceThickness>
			<canFilthAttach>true</canFilthAttach>
			<maxThickness>50</maxThickness>
			<cleaningSound>Interact_CleanFilth_Fluid</cleaningSound>
		</filth>
	</ThingDef>
	<ThingDef ParentName="BaseFilth">
		<defName>Filth_Mycelium</defName>
		<label>Mycelium</label>
		<useHitPoints>true</useHitPoints>
		<statBases>
			<Beauty>-4</Beauty>
			<Cleanliness>-4</Cleanliness>
			<MaxHitPoints>50</MaxHitPoints>
			<Flammability>4</Flammability>
		</statBases>
		<graphicData>
			<texPath>Core/Items/Mycelium</texPath>
			<graphicClass>Graphic_Random</graphicClass>
		</graphicData>
		<filth>
			<ignoreFilthMultiplierStat>true</ignoreFilthMultiplierStat>
			<rainWashes>false</rainWashes>
			<cleaningWorkToReduceThickness>250</cleaningWorkToReduceThickness>
			<canFilthAttach>true</canFilthAttach>
			<maxThickness>50</maxThickness>
			<cleaningSound>Interact_CleanFilth_Fluid</cleaningSound>
		</filth>
	</ThingDef>
</Defs>
