<?xml version="1.0" encoding="utf-8" ?>
<Defs>

	<BiomeDef>
		<defName>DankPyon_AncientForest</defName>
		<label>Ancient Forest</label>
		<description>Flatland covered in lylses and scara trees—the ancient biome is an arid place of clear skies and bright green elven trees with autumn-stained flora. Although much of the land is fertile, the crowded botany makes large cities a challenge while hiding camps and homesteads. An abundance of animals gather towards ancient biomes thanks to the various hiding spots found in trees, large flora, and crevasses that lead to caves. Some may find the biomes unsettling, as howling night winds carry whispers of the old gods.</description>
		<workerClass>DankPyon.BiomeWorker_AncientForest</workerClass>
		<animalDensity>2.8</animalDensity>
		<plantDensity>0.85</plantDensity>
		<implemented>true</implemented>
		<forageability>1</forageability>
		<foragedFood>RawBerries</foragedFood>
		<settlementSelectionWeight>1</settlementSelectionWeight>
		<texture>Biomes/AncientForest</texture>
		<soundsAmbient>
			<li>AmbientNightInsects_Standard</li>
		</soundsAmbient>
		<diseaseMtbDays>45</diseaseMtbDays>
		<diseases>
			<li>
				<diseaseInc>Disease_Flu</diseaseInc>
				<commonality>100</commonality>
			</li>
			<li>
				<diseaseInc>Disease_Plague</diseaseInc>
				<commonality>100</commonality>
			</li>
			<li>
				<diseaseInc>Disease_Malaria</diseaseInc>
				<commonality>100</commonality>
			</li>
			<li>
				<diseaseInc>Disease_FibrousMechanites</diseaseInc>
				<commonality>0</commonality>
			</li>
			<li>
				<diseaseInc>Disease_SensoryMechanites</diseaseInc>
				<commonality>0</commonality>
			</li>
			<li>
				<diseaseInc>Disease_GutWorms</diseaseInc>
				<commonality>50</commonality>
			</li>
			<li>
				<diseaseInc>Disease_MuscleParasites</diseaseInc>
				<commonality>50</commonality>
			</li>
		</diseases>
		<terrainsByFertility>
			<li>
			<terrain>Soil</terrain>
				<min>-999</min>
				<max>0.87</max>
			</li>
			<li>
			<terrain>SoilRich</terrain>
				<min>0.87</min>
				<max>999</max>
			</li>
		</terrainsByFertility>
		<terrainPatchMakers>
			<li>
				<perlinFrequency>0.015</perlinFrequency>
				<thresholds>
					<li>
						<terrain>MossyTerrain</terrain>
						<min>0.0</min>
						<max>0.32</max>
					</li>
					<li>
						<terrain>SoilRich</terrain>
						<min>0.62</min>
						<max>0.80</max>
					</li>
					<li>
						<terrain>Mud</terrain>
						<min>0.0</min>
						<max>0.32</max>
					</li>
					<li>
						<terrain>WaterShallow</terrain>
						<min>0.93</min>
						<max>1.06</max>
					</li>
					<li>
						<terrain>WaterDeep</terrain>
						<min>1.06</min>
						<max>999</max>
					</li>
				</thresholds>
			</li>
		</terrainPatchMakers>
		<baseWeatherCommonalities>
			<Rain>1</Rain>
			<DryThunderstorm>1</DryThunderstorm>
			<RainyThunderstorm>1</RainyThunderstorm>
			<FoggyRain>2</FoggyRain>
			<Fog>3</Fog>
			<SnowGentle>3</SnowGentle>
			<SnowHard>4</SnowHard>
			<Clear>17</Clear>
		</baseWeatherCommonalities>
		<wildPlants>
			<Plant_Healroot>0.08</Plant_Healroot>
			<Plant_Dandelion>0.2</Plant_Dandelion>
			<Plant_Berry>0.30</Plant_Berry>
			<Plant_Bush>0.4</Plant_Bush>
			<Plant_Grass>0.80</Plant_Grass>
			<Plant_TallGrass>0.80</Plant_TallGrass>
			<Plant_Brambles>1.0</Plant_Brambles>
			<!-- Trees -->
			<DankPyon_TreeScara>0.25</DankPyon_TreeScara>
			<DankPyon_TreeLylses>0.05</DankPyon_TreeLylses>
			<Plant_TreeOak>0.25</Plant_TreeOak>
			<Plant_TreeMaple>0.25</Plant_TreeMaple>
			<Plant_TreePoplar>0.35</Plant_TreePoplar>
		</wildPlants>
		<wildAnimals>
			<Hare>1.00</Hare>
			<Squirrel>1.00</Squirrel>
			<Rat>0.8</Rat>
			<Deer>0.5</Deer>
			<WildBoar>0.5</WildBoar>
			<Turkey>0.5</Turkey>
			<Raccoon>0.4</Raccoon>
			<Tortoise>0.4</Tortoise>
			<Ibex>0.3</Ibex>
			<Boomrat>0.25</Boomrat>
			<Muffalo>0.2</Muffalo>
			<DankPyon_Rox>0.3</DankPyon_Rox>
			<Boomalope>0.2</Boomalope>
			<Elk>0.3</Elk>
			<Wolf_Timber>0.04</Wolf_Timber>
			<DankPyon_Direwolf>0.04</DankPyon_Direwolf>
			<Fox_Red>0.04</Fox_Red>
			<Megasloth>0.04</Megasloth>
			<Bear_Grizzly>0.022</Bear_Grizzly>
			<Warg>0.012</Warg>
			<Cougar>0.012</Cougar>
			<Lynx>0.01</Lynx>
		</wildAnimals>
		<allowedPackAnimals>
			<li>Muffalo</li>
			<li>Alpaca</li>
		</allowedPackAnimals>
	</BiomeDef>

</Defs>